jumperless_pkg/__init__.py
jumperless_pkg/bridge.py
jumperless_pkg/cli.py
jumperless_pkg/assets/Boardpic.png
jumperless_pkg/assets/HalftoneStripes.png
jumperless_pkg/assets/JumperlessWokwiDMGwindow4x.png
jumperless_pkg/assets/NameSmall.png
jumperless_pkg/assets/avrdudeCustom.conf
jumperless_pkg/assets/example_sketch.ino
jumperless_pkg/assets/jogoTiny.png
jumperless_pkg/assets/icons/icon-0.png
jumperless_pkg/assets/icons/icon-1.png
jumperless_pkg/assets/icons/icon-2.png
jumperless_pkg/assets/icons/icon-3.png
jumperless_pkg/assets/icons/icon-4.png
jumperless_pkg/assets/icons/icon-5.png
jumperless_pkg/assets/icons/icon-6.png
jumperless_pkg/assets/icons/icon-7.png
jumperless_pkg/assets/icons/icon-8.png
jumperless_pkg/assets/icons/icon.icns
jumperless_pkg/assets/icons/icon.ico
jumperless_pkg/assets/icons/icon.png
jumperless_pkg/assets/icons/oldIcon/icon-0.png
jumperless_pkg/assets/icons/oldIcon/icon-1.png
jumperless_pkg/assets/icons/oldIcon/icon-2.png
jumperless_pkg/assets/icons/oldIcon/icon-3.png
jumperless_pkg/assets/icons/oldIcon/icon-4.png
jumperless_pkg/assets/icons/oldIcon/icon-5.png
jumperless_pkg/assets/icons/oldIcon/icon-6.png
jumperless_pkg/assets/icons/oldIcon/icon-7.png
jumperless_pkg/assets/icons/oldIcon/icon-8.png
jumperless_pkg/assets/icons/oldIcon/icon.icns
jumperless_pkg/assets/icons/oldIcon/icon.ico
jumperless_pkg/assets/icons/oldIcon/icon.png
jumperless-1.1.1.15.dist-info/METADATA
jumperless-1.1.1.15.dist-info/WHEEL
jumperless-1.1.1.15.dist-info/entry_points.txt
jumperless-1.1.1.15.dist-info/top_level.txt
jumperless-1.1.1.15.dist-info/RECORD
