Metadata-Version: 2.4
Name: jumperless
Version: 1.1.1.15
Summary: Jumperless Wokwi Bridge - Connect your Jumperless hardware to Wokwi projects and flash Arduino sketches
Author-email: Kevin Santo Cappuccio <KevinC@ppucc.io>
Project-URL: Homepage, https://jumperless.org
Project-URL: Documentation, https://jumperless.org
Project-URL: Repository, https://github.com/Architeuthis-Flux/Jumperless-App
Project-URL: Bug Tracker, https://github.com/Architeuthis-Flux/JumperlessV5/issues
Keywords: jumperless,wokwi,arduino,hardware,embedded,prototyping
Classifier: Development Status :: 4 - Beta
Classifier: Intended Audience :: Developers
Classifier: Intended Audience :: Education
Classifier: Topic :: Software Development :: Embedded Systems
Classifier: Topic :: System :: Hardware
Classifier: License :: OSI Approved :: GNU General Public License v3 or later (GPLv3+)
Classifier: Programming Language :: Python :: 3
Classifier: Programming Language :: Python :: 3.8
Classifier: Programming Language :: Python :: 3.9
Classifier: Programming Language :: Python :: 3.10
Classifier: Programming Language :: Python :: 3.11
Classifier: Programming Language :: Python :: 3.12
Classifier: Operating System :: OS Independent
Classifier: Operating System :: POSIX :: Linux
Classifier: Operating System :: MacOS
Classifier: Operating System :: Microsoft :: Windows
Requires-Python: >=3.8
Requires-Dist: beautifulsoup4>=4.13.4
Requires-Dist: packaging>=24.1
Requires-Dist: psutil>=5.9.8
Requires-Dist: pyduinocli>=0.35.0
Requires-Dist: pyserial>=3.5
Requires-Dist: requests>=2.32.3
Requires-Dist: colorama>=0.4.6
Requires-Dist: pywin32>=306; platform_system == "Windows"
Requires-Dist: pynput; platform_system == "Windows"
Provides-Extra: gui
Requires-Dist: PySide6>=6.6.0; extra == "gui"
Requires-Dist: websockets>=12.0; extra == "gui"
Provides-Extra: dev
Requires-Dist: build>=1.0.0; extra == "dev"
Requires-Dist: twine>=4.0.0; extra == "dev"
